{
    "id": 87441531,
    "name": "crazy challenge",
    "author": "taiga",
    "creators": ["taiga"],
    "verifier": "taiga",
    "verification": "https://youtu.be/ZZce23iNfFg",
    "password": "",
    "records": [
        {
            "user": "functionxd",
            "enjoyment": 100
        },
        {
            "user": "danz",
            "enjoyment": 100
        },
        {
            "user": "Algirdas42",
            "enjoyment": 100
        },
        {
            "user": "KandyMan",
            "enjoyment": 100
        },
        {
            "user": "xtrapnationx",
            "enjoyment": 100
        },
        {
            "user": "ta1p",
            "enjoyment": 100
        },
        {
            "user": "Slick",
            "enjoyment": 100
        },
        {
            "user": "S3N1",
            "link": "https://www.youtube.com/watch?v=4fJ7xGy1H9M",
            "enjoyment": 100
        }
        
    ]
}
